elevenlabs_wrapper/__init__.py
elevenlabs_wrapper/wrapper.py
elevenlabs_wrapper-0.0.6.dist-info/METADATA
elevenlabs_wrapper-0.0.6.dist-info/WHEEL
elevenlabs_wrapper-0.0.6.dist-info/licenses/LICENSE
elevenlabs_wrapper-0.0.6.dist-info/RECORD
