Metadata-Version: 2.3
Name: elevenlabs-wrapper
Version: 0.0.6
Summary: A simple wrapper for Elevenlabs TTS
Project-URL: Homepage, https://github.com/daswer123/sonic_tts_api_wrapper
Project-URL: Bug Tracker, https://github.com/daswer123/sonic_tts_api_wrapper/issues
Author-email: daswer123 <daswerq123@gmail.com>
Classifier: License :: OSI Approved :: MIT License
Classifier: Operating System :: OS Independent
Classifier: Programming Language :: Python :: 3
Requires-Python: >=3.9
Requires-Dist: elevenlabs
Requires-Dist: python-dotenv
